datav_twinfabric_mcp/__init__.py
datav_twinfabric_mcp/twinfabric_mcp_server.py
datav_twinfabric_mcp/tools/__init__.py
datav_twinfabric_mcp/tools/agent_app_tools.py
datav_twinfabric_mcp/tools/dtf_bailian_tools.py
datav_twinfabric_mcp/tools/dtf_opus_tools.py
datav_twinfabric_mcp/tools/dtf_project_tools.py
datav_twinfabric_mcp/tools/dtf_scene_understanding_tools.py
datav_twinfabric_mcp/tools/dtf_twin_tools.py
datav_twinfabric_mcp-1.4.1.dist-info/METADATA
datav_twinfabric_mcp-1.4.1.dist-info/WHEEL
datav_twinfabric_mcp-1.4.1.dist-info/entry_points.txt
datav_twinfabric_mcp-1.4.1.dist-info/top_level.txt
datav_twinfabric_mcp-1.4.1.dist-info/RECORD
