Metadata-Version: 2.4
Name: datav-twinfabric-mcp
Version: 1.4.1
Summary: DataV.TwinFabric MCP Server: A server for DataV.TwinFabric integration via the Model Context Protocol (MCP).
Author-email: 橙唯 <chenchengju.ccj@alibaba-inc.com>
Requires-Python: >=3.10
Requires-Dist: mcp[cli]>=1.4.1
Requires-Dist: fastmcp>=0.2.0
Requires-Dist: uvicorn
Requires-Dist: fastapi
Requires-Dist: pydantic>=2.6.1
Requires-Dist: dashscope
Requires-Dist: requests
